{
  "$schema":"http://json-schema.org/draft-04/schema#",
  "title":"metaData",
  "description":"mata data of 'Aird'",
  "type":"object",
  "properties":{
    "instruments":{
      "type":"array",
      "items":{
        "type":"array",
        "items":{
          "type":"object",
          "properties":{
            "manufacturer":{
              "type":"string"
            },
            "model":{
              "type":"string"
            },
            "source":{
              "type":"array",
              "items":{
                "type":"string"
              }
            },
            "analyzer":{
              "type":"array",
              "items":{
                "type":"string"
              }
            },
            "detector":{
              "type":"array",
              "items":{
                "type":"string"
              }
            }
          },
          "required":[]
        }
      }
    },
    "softwares":{
      "type":"array",
      "items":{
        "type":"object",
        "properties":{
          "name":{
            "type":"string"
          },
          "type":{
            "type":"string"
          },
          "version":{
            "type":"string"
          }
        },
        "required":[]
      }
    },
    "parentFiles":{
      "type":"array",
      "items":{
        "type":"object",
        "properties":{
          "name":{
            "type":"string"
          },
          "location":{
            "type":"string"
          },
          "formatType":{
            "type":"string"
          }
        },
        "required":[]
      }
    },
    "compressors":{
      "type":"array",
      "items":{
        "type":"object",
        "properties":{
          "precision":{
            "type":"integer"
          },
          "target":{
            "type":"string"
          },
          "methods":{
            "type":"array"
            "items":{
              "type":"string"
            }
          }
        },
        "required":[]
      }
    },
    "rangeList":{
      "type":"array",
      "items":{
        "type":"object",
        "properties":{
          "features":{
            "type":"string"
          },
          "start":{
            "type":"number"
          },
          "end":{
            "type":"number"
          },
          "mz":{
            "type":"number"
          }
        },
        "required":[]
      }
    },
    "indexList":{
      "type":"array",
      "items":{
        "type":"object",
        "properties":{
          "level":{
            "type":"integer"
          },
          "startPtr":{
            "type":"integer"
          },
          "endPtr":{
            "type":"integer"
          },
          "parentNum":{
            "type":"intger"
          },
          "nums":{
            "type":"array",
            "items":{
              "type":"integer"
            }
          },
          "rts":{
            "type":"array",
            "items":{
              "type":"number"
            }
          },
          "mzs":{
            "type":"array",
            "items":{
              "type":"integer"
            }
          },
          "ints":{
            "type":"array",
            "items":{
              "type":"integer"
            }
          }
        },
        "required":[]
      }
    },
    "type":{
      "type":"string",
    },
    "airdPath":{
      "type":"string",
    },
    "fileSize":{
      "type":"integer",
    },
    "totalScanCount":{
      "type":"integer",
    },
    "creator":{
      "type":"string",
    },
    "createDate":{
      "type":"string",
    },
    "features":{
      "type":"string",
    },
    "version":{
      "type":"string",
    },
    "versionCode":{
      "type":"integer",
    },
    "ignoreZeroIntensityPoint":{
      "type":"boolean",
    }
  },
  "required":[
  ]
}